instasave/LICENSE
instasave/__init__.py
instasave/__main__.py
instasave/save_post.py
instasave-0.3.1.dist-info/METADATA
instasave-0.3.1.dist-info/WHEEL
instasave-0.3.1.dist-info/licenses/LICENSE
instasave-0.3.1.dist-info/RECORD
