Metadata-Version: 2.3
Name: instasave
Version: 0.3.1
Summary: Download script for Instagram posts.
Project-URL: homepage, https://github.com/fsoubelet/InstaSave
Project-URL: repository, https://github.com/fsoubelet/InstaSave
Author-email: Felix Soubelet <felix.soubelet@cern.ch>
License-Expression: MIT
License-File: LICENSE
Keywords: Download,Instagram,Utility
Classifier: Development Status :: 4 - Beta
Classifier: License :: OSI Approved :: MIT License
Classifier: Natural Language :: English
Classifier: Programming Language :: Python
Classifier: Programming Language :: Python :: 3 :: Only
Classifier: Programming Language :: Python :: 3.9
Classifier: Programming Language :: Python :: 3.10
Classifier: Programming Language :: Python :: 3.11
Classifier: Programming Language :: Python :: 3.12
Classifier: Programming Language :: Python :: Implementation :: CPython
Classifier: Topic :: Utilities
Requires-Python: >=3.9
Requires-Dist: loguru<1.0
Requires-Dist: requests>=2.25
Requires-Dist: tqdm>=4.50
Requires-Dist: typer>=0.10
